pylint_quacking/__init__.py
pylint_quacking/quacking.py
pylint_quacking/test_quacking.py
pylint_quacking-0.1.2.dist-info/WHEEL
pylint_quacking-0.1.2.dist-info/METADATA
pylint_quacking-0.1.2.dist-info/RECORD
