Metadata-Version: 2.1
Name: pylint-quacking
Version: 0.1.2
Summary: Ban annotations. Ducks rule!
Home-page: https://github.com/weargoggles/pylint-quacking
License: MIT
Author: Pete Wildsmith
Author-email: pete@weargoggles.co.uk
Requires-Python: >=3.7,<4.0
Classifier: License :: OSI Approved :: MIT License
Classifier: Programming Language :: Python :: 3
Classifier: Programming Language :: Python :: 3.7
Classifier: Programming Language :: Python :: 3.8
Classifier: Programming Language :: Python :: 3.9
Requires-Dist: pylint (>=2.6.0,<3.0.0)
